screenselector/__init__.py
screenselector/_version.py
screenselector/screenselector.py
screenselector-1.0.0rc1.dist-info/LICENSE
screenselector-1.0.0rc1.dist-info/METADATA
screenselector-1.0.0rc1.dist-info/WHEEL
screenselector-1.0.0rc1.dist-info/entry_points.txt
screenselector-1.0.0rc1.dist-info/top_level.txt
screenselector-1.0.0rc1.dist-info/RECORD
