Metadata-Version: 2.1
Name: screenselector
Version: 1.0.0rc1
Summary: A small utility that allows selecting from running screen sessions by menu.
Home-page: https://github.com/mutax/screenselector
Author: Florian Streibelt
Author-email: pypi@streibelt.net
License: UNKNOWN
Platform: UNKNOWN
Classifier: Programming Language :: Python :: 3
Classifier: License :: OSI Approved :: MIT License
Classifier: Operating System :: OS Independent
Requires-Python: >=3.5
